{"Ami Gal":{"daysWorked":24,"fte":100},"Razi Shoshani":{"daysWorked":23,"fte":100},"Or Cohen":{"daysWorked":21,"fte":100},"Eyal Weisblat":{"daysWorked":23,"fte":100},"Saray Ben-Meir":{"daysWorked":22,"fte":80},"Amihai Grossman":{"daysWorked":23,"fte":100},"Omer Tati":{"daysWorked":20,"fte":100},"Slavi Khodorkovsky":{"daysWorked":21,"fte":100},"Daniel Gutman":{"daysWorked":22,"fte":100},"Aviv Shemesh":{"daysWorked":20,"fte":100},"Shmuel Hanoch":{"daysWorked":17,"fte":100},"Inbar Biri":{"daysWorked":19,"fte":100},"Alex Karpov":{"daysWorked":22,"fte":100},"Tal Kron":{"daysWorked":22,"fte":100},"Sharon Sasson":{"daysWorked":23,"fte":100},"Lital Weiss":{"daysWorked":21,"fte":100},"Gal Lalouche":{"daysWorked":23,"fte":100},"Ariel Nahum":{"daysWorked":22,"fte":100},"Hani Lifshitz":{"daysWorked":21,"fte":100},"Sagi Bachar":{"daysWorked":22,"fte":100},"Yael Weiss":{"daysWorked":23,"fte":50},"Avi Sagi":{"daysWorked":23,"fte":100},"Yotam Steinberg":{"daysWorked":22,"fte":100},"Dor Berg":{"daysWorked":22,"fte":100},"Ahmad Sharabati":{"daysWorked":20,"fte":100},"Mohammed Imad":{"daysWorked":20,"fte":100},"Ben Wellingstein":{"daysWorked":19,"fte":100},"Daniel Rempel":{"daysWorked":23,"fte":100},"Efrat Mordechay":{"daysWorked":15,"fte":100},"Mor Arbiv":{"daysWorked":22,"fte":100},"Ron Eliyahu":{"daysWorked":23,"fte":100},"Itiel Sadeh":{"daysWorked":22,"fte":100},"Ohad Shalev":{"daysWorked":23,"fte":100},"Shahar Faians":{"daysWorked":22,"fte":100},"Raz Kaplan Raviv":{"daysWorked":22,"fte":100},"Mordehai German":{"daysWorked":23,"fte":100},"Elad Zicherman":{"daysWorked":23,"fte":100},"Yaniv Leven":{"daysWorked":19,"fte":100},"Ilia Tenkalevich":{"daysWorked":22,"fte":100},"Georgy Adamskiy":{"daysWorked":21,"fte":100},"Vladimir (Vova) Platonov":{"daysWorked":23,"fte":100},"Yoni Levy":{"daysWorked":23,"fte":100},"Yoav Ron":{"daysWorked":23,"fte":100},"Roy Selinko":{"daysWorked":23,"fte":100},"Danelle Ben Ari":{"daysWorked":23,"fte":100},"Dima Dobrinsky":{"daysWorked":20,"fte":100},"Sharon Lahav":{"daysWorked":23,"fte":100},"Evgeni Koifman":{"daysWorked":24,"fte":100},"Noa Sarai Attias":{"daysWorked":23,"fte":100},"Matan Libis":{"daysWorked":22,"fte":100},"Or Tzadik":{"daysWorked":22,"fte":100},"Oryan Abergel":{"daysWorked":23,"fte":100},"Idan Osteraicher":{"daysWorked":22,"fte":100},"Yuval Shtemer":{"daysWorked":0,"fte":100},"Michael Tubul":{"daysWorked":0,"fte":100},"Udi Keidar":{"daysWorked":21,"fte":100},"Omri Levy":{"daysWorked":23,"fte":100},"Zachi Kochman":{"daysWorked":0,"fte":100},"Adva Blanco":{"daysWorked":23,"fte":100},"Leora Ann Kudo":{"daysWorked":26,"fte":100},"Rotem Shaltiel":{"daysWorked":7,"fte":100},"Benny Rubinstein":{"daysWorked":23,"fte":100},"Sagi Forbes Nagar":{"daysWorked":22,"fte":100},"Adi Peretz":{"daysWorked":23,"fte":100},"Dandan Ogni":{"daysWorked":15,"fte":80},"Loay Naser":{"daysWorked":22,"fte":100},"Ayelet Ofir":{"daysWorked":17,"fte":50},"Ariel Biran":{"daysWorked":23,"fte":100},"Netaly Avizoor":{"daysWorked":23,"fte":100},"Alex Shtromberg":{"daysWorked":22,"fte":100},"Yuval Ramati":{"daysWorked":0,"fte":100},"Ron Forsher":{"daysWorked":21,"fte":100},"Shiri Dorot":{"daysWorked":1,"fte":100},"Leah Hazan":{"daysWorked":21,"fte":100},"Efrat Cohen":{"daysWorked":23,"fte":100},"Yotam Kramer":{"daysWorked":23,"fte":100},"Ariel Wagowsky":{"daysWorked":22,"fte":100},"Carmit Baron Siton":{"daysWorked":23,"fte":100},"Ivan Shepelenko":{"daysWorked":21,"fte":100},"Mulat Mekonen":{"daysWorked":22,"fte":100},"Inna Schneiderman":{"daysWorked":23,"fte":100},"Tomer Wolff":{"daysWorked":22,"fte":100},"Gilad Shay":{"daysWorked":22,"fte":100},"Noga Eshet":{"daysWorked":22,"fte":100},"Nilly Ofan Zandberg":{"daysWorked":23,"fte":100},"Diana Simonova":{"daysWorked":7,"fte":30},"Talia Rosin":{"daysWorked":22,"fte":100},"Shai Shalev":{"daysWorked":0,"fte":100},"Tomer Levi":{"daysWorked":23,"fte":100},"Johnny Lichtblau":{"daysWorked":21,"fte":100},"Shahar Ben Moha":{"daysWorked":23,"fte":100},"Etai Chai Shimoni":{"daysWorked":23,"fte":100},"Rani Rimon":{"daysWorked":0,"fte":100},"Ruth Apter":{"daysWorked":22,"fte":100},"Tal Aharon":{"daysWorked":23,"fte":100}}